octa/Positions.py
octa/Stimulus.py
octa/__init__.py
octa/measurements/Complexity.py
octa/measurements/Order.py
octa/measurements/__init__.py
octa/patterns/GridPattern.py
octa/patterns/Pattern.py
octa/patterns/__init__.py
octa/shapes/Ellipse.py
octa/shapes/FitImage.py
octa/shapes/Image.py
octa/shapes/Path.py
octa/shapes/PathSvg.py
octa/shapes/Polygon.py
octa/shapes/Rectangle.py
octa/shapes/RegularPolygon.py
octa/shapes/Text.py
octa/shapes/Triangle.py
octa/shapes/__init__.py
octa-1.0.1.dist-info/COPYING.LESSER.txt
octa-1.0.1.dist-info/COPYING.txt
octa-1.0.1.dist-info/LICENSE.txt
octa-1.0.1.dist-info/METADATA
octa-1.0.1.dist-info/WHEEL
octa-1.0.1.dist-info/top_level.txt
octa-1.0.1.dist-info/RECORD
