Metadata-Version: 2.1
Name: octa
Version: 1.0.1
Summary: A tool for researchers to create stimuli varying in order and complexity on different dimensions
Home-page: https://github.com/gestaltrevision/OCTA_toolbox
Author: Eline Van Geert, Christophe Bossens, and Johan Wagemans
Author-email: eline.vangeert@kuleuven.be
Project-URL: Issue Tracker, https://github.com/gestaltrevision/OCTA_toolbox/issues
Classifier: Programming Language :: Python :: 3
Classifier: License :: OSI Approved :: GNU Lesser General Public License v3 or later (LGPLv3+)
Classifier: Operating System :: OS Independent
Requires-Python: >=3.6
License-File: LICENSE.txt
License-File: COPYING.LESSER.txt
License-File: COPYING.txt
